{
    "name": "Task",
    "fields": [
        {
            "fieldName": "name",
            "fieldType": "String",
            "fieldValidateRules": [
                "required",
                "minlength",
                "maxlength"
            ],
            "fieldValidateRulesMinlength": 5,
            "fieldValidateRulesMaxlength": 200
        },
        {
            "fieldName": "createdByUser",
            "fieldType": "String"
        },
        {
            "fieldName": "createdDate",
            "fieldType": "Instant"
        },
        {
            "fieldName": "lastModifiedByUser",
            "fieldType": "String"
        },
        {
            "fieldName": "lastModifiedDate",
            "fieldType": "Instant"
        }
    ],
    "relationships": [],
    "changelogDate": "20191225215915",
    "entityTableName": "task",
    "dto": "no",
    "pagination": "infinite-scroll",
    "service": "no",
    "jpaMetamodelFiltering": false,
    "fluentMethods": true,
    "clientRootFolder": "",
    "applications": "*",
    "skipServer": true
}